airtop/__init__.py
airtop/automations/__init__.py
airtop/automations/client.py
airtop/base_client.py
airtop/client.py
airtop/core/__init__.py
airtop/core/api_error.py
airtop/core/client_wrapper.py
airtop/core/datetime_utils.py
airtop/core/file.py
airtop/core/http_client.py
airtop/core/jsonable_encoder.py
airtop/core/pydantic_utilities.py
airtop/core/query_encoder.py
airtop/core/remove_none_from_dict.py
airtop/core/request_options.py
airtop/core/serialization.py
airtop/environment.py
airtop/errors/__init__.py
airtop/errors/forbidden_error.py
airtop/errors/internal_server_error.py
airtop/errors/not_found_error.py
airtop/errors/unauthorized_error.py
airtop/errors/unprocessable_entity_error.py
airtop/files/__init__.py
airtop/files/client.py
airtop/files/types/__init__.py
airtop/files/types/create_file_rest_input_v1file_type.py
airtop/profiles/__init__.py
airtop/profiles/client.py
airtop/py.typed
airtop/requests/__init__.py
airtop/requests/client.py
airtop/sessions/__init__.py
airtop/sessions/client.py
airtop/sessions/types/__init__.py
airtop/sessions/types/sessions_events_response.py
airtop/sessions/types/sessions_events_response_captcha_event.py
airtop/sessions/types/sessions_events_response_error.py
airtop/sessions/types/sessions_events_response_file_event.py
airtop/sessions/types/sessions_events_response_session_event.py
airtop/sessions/types/sessions_events_response_status.py
airtop/sessions/types/sessions_events_response_window_event.py
airtop/sessions/types/sessions_list_request_status.py
airtop/types/__init__.py
airtop/types/ai_prompt_response.py
airtop/types/ai_response_envelope.py
airtop/types/airtop_proxy_configuration.py
airtop/types/async_config.py
airtop/types/async_session_ai_response_envelope.py
airtop/types/automation_output.py
airtop/types/browser_wait_navigation_config.py
airtop/types/browser_wait_navigation_config_wait_until.py
airtop/types/captcha_event_message.py
airtop/types/captcha_event_message_status.py
airtop/types/click_config.py
airtop-0.0.49.dist-info/LICENSE
airtop-0.0.49.dist-info/METADATA
airtop-0.0.49.dist-info/WHEEL
airtop-0.0.49.dist-info/RECORD
